deflate.so
deflate-0.7.0.dist-info/METADATA
deflate-0.7.0.dist-info/RECORD
deflate-0.7.0.dist-info/WHEEL
deflate-0.7.0.dist-info/licenses/LICENSE
